rgram/__init__.py
rgram/base.py
rgram/dclasses.py
rgram/rgram.py
rgram/smoothing.py
rgram-0.1.0.dist-info/METADATA
rgram-0.1.0.dist-info/WHEEL
rgram-0.1.0.dist-info/licenses/LICENSE
rgram-0.1.0.dist-info/RECORD
