Metadata-Version: 2.4
Name: rgram
Version: 0.1.0
Summary: A Python library for regressograms and kernel smoothing, designed for data analysis and visualisation.
Author: Jack
License-File: LICENSE
Requires-Python: >=3.11
Requires-Dist: polars-ols>=0.3.5
Requires-Dist: polars>=1.28.1
